quali_bus/__init__.py
quali_bus/data_analysis/__init__.py
quali_bus/data_analysis/calcular_indicadores.py
quali_bus/data_analysis/carregar_dados.py
quali_bus/data_analysis/classificar_indicadores.py
quali_bus/facade.py
quali_bus/map_tools/__init__.py
quali_bus/map_tools/camadas.py
quali_bus/map_tools/criacao_mapa.py
quali_bus/utils/__init__.py
quali_bus/utils/associador.py
quali_bus/utils/config.py
quali_bus/utils/cores.py
quali_bus/utils/modelos.py
quali_bus/utils/utils.py
quali_bus/visualization/__init__.py
quali_bus/visualization/visualizacao_bairros.py
quali_bus-0.3.1.dist-info/LICENSE
quali_bus-0.3.1.dist-info/METADATA
quali_bus-0.3.1.dist-info/WHEEL
quali_bus-0.3.1.dist-info/RECORD
