Metadata-Version: 2.3
Name: quali_bus
Version: 0.3.1
Summary: Automatizar o cálculo do Índice de Qualidade do Transporte (IQT). O IQT é uma métrica essencial para a análise e otimização do transporte público, considerando fatores como pontualidade, frequência de atendimento, cumprimento de itinerários e infraestrutura.
License: Apache-2.0
Keywords: transporte,IQT,GIS,análise espacial,transporte público
Author: Yago Maia
Author-email: yagohenriquev123@gmail.com
Requires-Python: >=3.12,<4.0
Classifier: License :: OSI Approved :: Apache Software License
Classifier: Programming Language :: Python :: 3
Classifier: Programming Language :: Python :: 3.12
Classifier: Programming Language :: Python :: 3.13
Requires-Dist: contextily (>=1.6.2,<2.0.0)
Requires-Dist: fiona (>=1.10.1,<2.0.0)
Requires-Dist: folium (>=0.19.7,<0.20.0)
Requires-Dist: geopandas (>=1.1.0,<2.0.0)
Requires-Dist: mapclassify (>=2.9.0,<3.0.0)
Requires-Dist: matplotlib (>=3.10.3,<4.0.0)
Requires-Dist: numpy (>=2.3.0,<3.0.0)
Requires-Dist: pandas (>=2.3.0,<3.0.0)
Requires-Dist: seaborn (>=0.13.2,<0.14.0)
Requires-Dist: shapely (>=2.1.1,<3.0.0)
Project-URL: Homepage, https://github.com/YagoMaia/quali_bus
Project-URL: Repository, https://github.com/YagoMaia/quali_bus
